ppager/__init__.py
ppager/ppager.py
ppager/run_ppager.py
ppager-0.1.1.dist-info/LICENSE
ppager-0.1.1.dist-info/METADATA
ppager-0.1.1.dist-info/WHEEL
ppager-0.1.1.dist-info/entry_points.txt
ppager-0.1.1.dist-info/top_level.txt
ppager-0.1.1.dist-info/RECORD
